Zoomba/APILibrary.py
Zoomba/DesktopLibrary.py
Zoomba/GUILibrary.py
Zoomba/MobileLibrary.py
Zoomba/SOAPLibrary.py
Zoomba/__init__.py
testfors/APILibrary.py
testfors/DesktopLibrary.py
testfors/GUILibrary.py
testfors/MobileLibrary.py
testfors/SOAPLibrary.py
testfors/__init__.py
robotframework_testfors-2.4.1.dist-info/LICENSE
robotframework_testfors-2.4.1.dist-info/METADATA
robotframework_testfors-2.4.1.dist-info/WHEEL
robotframework_testfors-2.4.1.dist-info/top_level.txt
robotframework_testfors-2.4.1.dist-info/RECORD
