Metadata-Version: 2.1
Name: robotframework-testfors
Version: 2.4.1
Summary: Robot Framework mini-framework.
Home-page: https://github.com/Accruent/zoomba
Maintainer: zwang
Maintainer-email: 836425419@qq.com
License: GPL-3.0
Keywords: Robot Framework robot-framework selenium requests appium soap winappdriver appium robotframeworkdesktop windows zoomba python robotframework-library appium-windows appiumlibrary api-rest api soap-api appium-mobile mobile
Platform: any
Classifier: Development Status :: 5 - Production/Stable
Classifier: Operating System :: OS Independent
Classifier: Programming Language :: Python :: 3
Classifier: Topic :: Software Development :: Testing
Classifier: Framework :: Robot Framework :: Library
Requires-Dist: robotframework (==3.2.1)
Requires-Dist: robotframework-requests (==0.7.0)
Requires-Dist: robotframework-seleniumlibrary (==4.4.0)
Requires-Dist: robotframework-sudslibrary-aljcalandra (==1.1)
Requires-Dist: requests (==2.24.0)
Requires-Dist: selenium (==3.141.0)
Requires-Dist: python-dateutil (==2.8.1)
Requires-Dist: robotframework-appiumlibrary (==1.5.0.6)
Provides-Extra: testing
Requires-Dist: Appium-Python-Client ; extra == 'testing'
